CHANGES.rst
MANIFEST.in
README.rst
development.ini
requirements.txt
setup.py
superdash/__init__.py
superdash/tests.py
superdash/views.py
superdash.egg-info/PKG-INFO
superdash.egg-info/SOURCES.txt
superdash.egg-info/dependency_links.txt
superdash.egg-info/entry_points.txt
superdash.egg-info/not-zip-safe
superdash.egg-info/requires.txt
superdash.egg-info/top_level.txt
superdash/static/css/bootstrap-theme.css
superdash/static/css/bootstrap.css
superdash/static/css/font-awesome.css
superdash/static/css/main.css
superdash/static/js/vendor/bootstrap.js
superdash/static/js/vendor/jquery-1.11.1.js
superdash/static/js/vendor/modernizr-2.6.2.min.js
superdash/templates/layout.mako
superdash/templates/list.mako
superdash/templates/mytemplate.pt